memorylayer_server/__init__.py
memorylayer_server/cli.py
memorylayer_server/config.py
memorylayer_server/dependencies.py
memorylayer_server/main.py
memorylayer_server/api/__init__.py
memorylayer_server/api/v1/__init__.py
memorylayer_server/api/v1/associations.py
memorylayer_server/api/v1/health.py
memorylayer_server/api/v1/memories.py
memorylayer_server/api/v1/schemas.py
memorylayer_server/api/v1/sessions.py
memorylayer_server/api/v1/workspaces.py
memorylayer_server/auth/__init__.py
memorylayer_server/auth/api_keys.py
memorylayer_server/auth/context.py
memorylayer_server/auth/middleware.py
memorylayer_server/auth/rbac.py
memorylayer_server/mcp/__init__.py
memorylayer_server/mcp/example.py
memorylayer_server/mcp/handlers.py
memorylayer_server/mcp/server.py
memorylayer_server/mcp/tools.py
memorylayer_server/mcp/validate.py
memorylayer_server/models/__init__.py
memorylayer_server/models/association.py
memorylayer_server/models/authz.py
memorylayer_server/models/category.py
memorylayer_server/models/llm.py
memorylayer_server/models/memory.py
memorylayer_server/models/resource.py
memorylayer_server/models/session.py
memorylayer_server/models/workspace.py
memorylayer_server/services/__init__.py
memorylayer_server/services/association/__init__.py
memorylayer_server/services/association/base.py
memorylayer_server/services/association/default.py
memorylayer_server/services/authorization/__init__.py
memorylayer_server/services/authorization/base.py
memorylayer_server/services/authorization/default.py
memorylayer_server/services/cache/__init__.py
memorylayer_server/services/cache/base.py
memorylayer_server/services/cache/noop.py
memorylayer_server/services/embedding/__init__.py
memorylayer_server/services/embedding/base.py
memorylayer_server/services/embedding/local.py
memorylayer_server/services/embedding/mock.py
memorylayer_server/services/embedding/openai.py
memorylayer_server/services/embedding/qwen3vl.py
memorylayer_server/services/embedding/service_default.py
memorylayer_server-0.0.1.post1.dist-info/METADATA
memorylayer_server-0.0.1.post1.dist-info/WHEEL
memorylayer_server-0.0.1.post1.dist-info/entry_points.txt
memorylayer_server-0.0.1.post1.dist-info/licenses/LICENSE
memorylayer_server-0.0.1.post1.dist-info/RECORD
