Metadata-Version: 2.4
Name: memorylayer-server
Version: 0.0.1.post1
Summary: MemoryLayer.ai - API-first memory infrastructure for LLM-powered agents (open source core)
Project-URL: Homepage, https://memorylayer.ai
Project-URL: Documentation, https://docs.memorylayer.ai
Project-URL: Repository, https://github.com/scitrera/memorylayer
Project-URL: Issues, https://github.com/scitrera/memorylayer/issues
Author-email: Scitrera <open-source-team@scitrera.com>
License: Apache 2.0
License-File: LICENSE
Keywords: agents,ai,llm,mcp,memory,rag,vector-search
Classifier: Development Status :: 3 - Alpha
Classifier: Intended Audience :: Developers
Classifier: License :: OSI Approved :: Apache Software License
Classifier: Programming Language :: Python :: 3
Classifier: Programming Language :: Python :: 3.12
Classifier: Topic :: Scientific/Engineering :: Artificial Intelligence
Requires-Python: >=3.12
Requires-Dist: aiosqlite>=0.22.1
Requires-Dist: click>=8.3.1
Requires-Dist: fastapi>=0.128.0
Requires-Dist: httpx>=0.28.1
Requires-Dist: mcp>=1.0.0
Requires-Dist: numpy>=1.26.0
Requires-Dist: pydantic-settings>=2.12.0
Requires-Dist: pydantic>=2.12.5
Requires-Dist: python-multipart>=0.0.22
Requires-Dist: scitrera-app-framework>=0.0.62
Requires-Dist: sqlalchemy[asyncio]>=2.0.46
Requires-Dist: uvicorn[standard]>=0.30.0
Provides-Extra: all
Requires-Dist: accelerate>=1.12.0; extra == 'all'
Requires-Dist: colpali-engine>=0.3.13; extra == 'all'
Requires-Dist: mypy>=1.19.1; extra == 'all'
Requires-Dist: openai>=1.109.1; extra == 'all'
Requires-Dist: pillow>=12.1.0; extra == 'all'
Requires-Dist: pytest-asyncio>=1.3.0; extra == 'all'
Requires-Dist: pytest-cov>=7.0.0; extra == 'all'
Requires-Dist: pytest>=9.0.2; extra == 'all'
Requires-Dist: respx>=0.22.0; extra == 'all'
Requires-Dist: ruff>=0.14.14; extra == 'all'
Requires-Dist: sentence-transformers>=5.2.2; extra == 'all'
Requires-Dist: tiktoken>=0.12.0; extra == 'all'
Requires-Dist: torch>=2.9.1; extra == 'all'
Requires-Dist: transformers<5; extra == 'all'
Provides-Extra: colpali
Requires-Dist: colpali-engine>=0.3.13; extra == 'colpali'
Requires-Dist: pillow>=12.1.0; extra == 'colpali'
Requires-Dist: torch>=2.9.1; extra == 'colpali'
Provides-Extra: dev
Requires-Dist: mypy>=1.19.1; extra == 'dev'
Requires-Dist: pytest-asyncio>=1.3.0; extra == 'dev'
Requires-Dist: pytest-cov>=7.0.0; extra == 'dev'
Requires-Dist: pytest>=9.0.2; extra == 'dev'
Requires-Dist: respx>=0.22.0; extra == 'dev'
Requires-Dist: ruff>=0.14.14; extra == 'dev'
Provides-Extra: embeddings
Requires-Dist: accelerate>=1.12.0; extra == 'embeddings'
Requires-Dist: colpali-engine>=0.3.13; extra == 'embeddings'
Requires-Dist: openai>=1.109.1; extra == 'embeddings'
Requires-Dist: pillow>=12.1.0; extra == 'embeddings'
Requires-Dist: sentence-transformers>=5.2.2; extra == 'embeddings'
Requires-Dist: tiktoken>=0.12.0; extra == 'embeddings'
Requires-Dist: torch>=2.9.1; extra == 'embeddings'
Requires-Dist: transformers<5; extra == 'embeddings'
Provides-Extra: local
Requires-Dist: sentence-transformers>=5.2.2; extra == 'local'
Provides-Extra: multimodal
Requires-Dist: accelerate>=1.12.0; extra == 'multimodal'
Requires-Dist: pillow>=12.1.0; extra == 'multimodal'
Requires-Dist: torch>=2.9.1; extra == 'multimodal'
Requires-Dist: transformers<5; extra == 'multimodal'
Provides-Extra: openai
Requires-Dist: openai>=1.109.1; extra == 'openai'
Requires-Dist: tiktoken>=0.12.0; extra == 'openai'
Provides-Extra: vllm
Requires-Dist: vllm>=0.14.1; extra == 'vllm'
